{
  "metadata": {
    "store_code": "1710309E11",
    "analysis_timestamp": "20251023_184234",
    "analysis_type": "comprehensive_analysis"
  },
  "spatial_analysis": {
    "address": "서울 성동구 왕십리로31나길 33.",
    "coordinates": [
      37.5635478,
      127.0286756
    ],
    "administrative_dong": "왕십리2동",
    "marketplace": {
      "상권명": "A",
      "거리_m": 0
    }
  },
  "store_summary": {
    "store_name": "24*********",
    "industry": "카페",
    "commercial_area": "상왕십리역 6번",
    "quality_score": 0.87
  },
  "marketing_summary": {
    "persona_type": "상왕십리_영_트렌드_탐색가",
    "risk_level": "낮음",
    "strategy_count": 0,
    "campaign_count": 0
  },
  "panorama_summary": {
    "area_characteristics": "이 지역은 주거와 생활 밀착형 상업 시설이 혼재된 조용한 이면 도로 상권입니다. 전반적으로 활발한 상업 활동보다는 지역 주민의 일상생활 편의를 위한 기능에 초점을 맞춘 차분하고 정돈된 분위기를 가지고 있습니다.",
    "marketplace_type": "근린형 생활상가",
    "scores": {
      "commercial_atmosphere": 3,
      "street_atmosphere": 6,
      "cleanliness": 7,
      "maintenance": 6,
      "walkability": 6,
      "safety_perception": 6,
      "business_diversity": 3,
      "residential_suitability": 8,
      "commercial_suitability": 3
    },
    "strengths": [
      "안정적인 주거 인구를 기반으로 한 생활 밀착형 서비스 수요가 존재합니다.",
      "조용하고 정돈된 분위기로, 주민들에게 쾌적한 주거 환경을 제공합니다.",
      "기존 상점 수가 적어 특정 니치 업종에 대한 경쟁 강도가 낮습니다."
    ],
    "weaknesses": [
      "모든 지점에서 '조용함'이 강조되어 유동 인구가 매우 적고 상권 활력이 낮습니다.",
      "상업 시설의 밀집도가 낮고 업종 다양성이 부족하여 상업적 매력이 떨어집니다.",
      "이면 도로에 위치하여 가시성이 낮고, 외부 유입 고객을 기대하기 어렵습니다."
    ],
    "recommended_industries": null,
    "expert_opinion": null
  },
  "marketplace_summary": {
    "marketplace_name": "상왕십리역 3번",
    "store_count": null,
    "sales_volume": null
  },
  "mobility_summary": {
    "analysis_period": null,
    "total_charts": 0
  },
  "new_product_summary": {
    "activated": false,
    "proposal_count": 0,
    "target_audience": {},
    "used_categories": []
  }
}